src/twittersent/__init__.py
src/twittersent/dateselect.py
src/twittersent/keyword_search.py
src/twittersent/makescript.py
src/twittersent/parse_sentiment.py
src/twittersent/plot_sent.py
src/twittersent/store_data.py
src/twittersent/twitterquery.py
twitter_sentiment_tracker-0.0.4.dist-info/METADATA
twitter_sentiment_tracker-0.0.4.dist-info/WHEEL
twitter_sentiment_tracker-0.0.4.dist-info/licenses/LICENSE
twitter_sentiment_tracker-0.0.4.dist-info/RECORD
