Metadata-Version: 2.1
Name: twitter-sentiment-tracker
Version: 0.0.4
Summary: A package for tracking historical sentiment data from Twitter over certain keywords
Project-URL: Homepage, https://github.com/pypa/twitter-sentiment-tracker
Project-URL: Bug Tracker, https://github.com/pypa/twitter-sentiment-tracker/issues
Author-email: Mitchell Hoikka <mitchell.hoikka1@gmail.com>
License: Copyright (c) 2018 The Python Packaging Authority
Classifier: License :: OSI Approved :: MIT License
Classifier: Operating System :: OS Independent
Classifier: Programming Language :: Python :: 3
Requires-Python: >=3.7
